{
  "enriched_at": "2026-04-04T05:22:17.458300+00:00",
  "elapsed_sec": 1.72,
  "count": 5,
  "tradeable_count": 0,
  "opportunities": [
    {
      "ts": "2026-04-04T05:15:41.400875+00:00",
      "strategy": "s1_negrisk_arb",
      "market_id": "0x649754f48cd224feb6c659216896195f3249155b6f77967056b2e5d99f622f00",
      "question": "NegRisk group: Will Hamburger SV win on 2026-04-04?...",
      "action": "BUY_ALL_YES",
      "score": 0.9813,
      "edge": 0.2183,
      "win_probability": 1.0,
      "buy_price": 0.7,
      "ev": 0.0,
      "kelly_frac": 0.0,
      "ttl_sec": 29663,
      "executed": false,
      "reason_skipped": "daily_loss_limit",
      "trade_id": "",
      "budget_usdc": 1.0,
      "shares": 1,
      "actual_cost": 0.7,
      "unused_cash": 0.3,
      "category": "sports",
      "volume_24h": 8494.38,
      "spread": 0,
      "fee": 0,
      "minutes_left": 494.4,
      "days_left": 0.34,
      "num_legs": 2,
      "total_ask": 0.7,
      "observer_flagged": false,
      "clob_enriched": false,
      "error": "gamma_fetch_failed"
    },
    {
      "ts": "2026-04-04T05:15:41.412215+00:00",
      "strategy": "s1_negrisk_arb",
      "market_id": "0xf2778088401fcb46e62ebaa07e88080e5f988041aad8f8c21042c4d2855ebc00",
      "question": "NegRisk group: Will the highest temperature in Dallas be between 76-77\u00b0F on...",
      "action": "BUY_ALL_YES",
      "score": 0.9774,
      "edge": 0.6673,
      "win_probability": 1.0,
      "buy_price": 0.309,
      "ev": 0.0,
      "kelly_frac": 0.0,
      "ttl_sec": 24262,
      "executed": false,
      "reason_skipped": "daily_loss_limit",
      "trade_id": "",
      "budget_usdc": 1.0,
      "shares": 1,
      "actual_cost": 0.309,
      "unused_cash": 0.691,
      "category": "other",
      "volume_24h": 5295.5,
      "spread": 0,
      "fee": 0,
      "minutes_left": 404.4,
      "days_left": 0.28,
      "num_legs": 2,
      "total_ask": 0.309,
      "observer_flagged": false,
      "clob_enriched": false,
      "error": "gamma_fetch_failed"
    },
    {
      "ts": "2026-04-04T05:15:41.423509+00:00",
      "strategy": "s1_negrisk_arb",
      "market_id": "0x34a03ad2e3d9c2caab6c54b62542de6848a2dddde19d2f66e97a44b94cc15800",
      "question": "NegRisk group: Will the highest temperature in Seattle be between 60-61\u00b0F o...",
      "action": "BUY_ALL_YES",
      "score": 0.9761,
      "edge": 0.5771,
      "win_probability": 1.0,
      "buy_price": 0.39,
      "ev": 0.0,
      "kelly_frac": 0.0,
      "ttl_sec": 24260,
      "executed": false,
      "reason_skipped": "daily_loss_limit",
      "trade_id": "",
      "budget_usdc": 1.0,
      "shares": 1,
      "actual_cost": 0.39,
      "unused_cash": 0.61,
      "category": "other",
      "volume_24h": 4591.84,
      "spread": 0,
      "fee": 0,
      "minutes_left": 404.3,
      "days_left": 0.28,
      "num_legs": 2,
      "total_ask": 0.39,
      "observer_flagged": false,
      "clob_enriched": false,
      "error": "gamma_fetch_failed"
    },
    {
      "ts": "2026-04-04T05:15:41.434880+00:00",
      "strategy": "s1_negrisk_arb",
      "market_id": "0xd066c8080d76bdf50ab2266b2ae037cc87f5ac7b30f54a5f6e58a605877b2600",
      "question": "NegRisk group: Will Ludvig Aberg win the 2026 Valero Texas Open?...",
      "action": "BUY_ALL_YES",
      "score": 0.9692,
      "edge": 0.7955,
      "win_probability": 1.0,
      "buy_price": 0.198,
      "ev": 0.0,
      "kelly_frac": 0.0,
      "ttl_sec": 67461,
      "executed": false,
      "reason_skipped": "daily_loss_limit",
      "trade_id": "",
      "budget_usdc": 1.0,
      "shares": 1,
      "actual_cost": 0.198,
      "unused_cash": 0.802,
      "category": "sports",
      "volume_24h": 3124.12,
      "spread": 0,
      "fee": 0,
      "minutes_left": 1124.3,
      "days_left": 0.78,
      "num_legs": 2,
      "total_ask": 0.198,
      "observer_flagged": false,
      "clob_enriched": false,
      "error": "gamma_fetch_failed"
    },
    {
      "ts": "2026-04-04T05:15:41.387943+00:00",
      "strategy": "s10_near_resolution",
      "market_id": "1553288",
      "question": "Will Chelsea FC win on 2026-04-04?",
      "action": "BUY_YES",
      "score": 0.7826,
      "edge": 0.0533,
      "win_probability": 0.935,
      "buy_price": 0.94,
      "ev": -0.0125,
      "kelly_frac": 0.0,
      "ttl_sec": 31462,
      "executed": false,
      "reason_skipped": "daily_loss_limit",
      "trade_id": "",
      "budget_usdc": 1.0,
      "shares": 1,
      "actual_cost": 0.94,
      "unused_cash": 0.06,
      "category": "sports",
      "volume_24h": 4121.01,
      "spread": 0.01,
      "fee": 0.006728,
      "minutes_left": 524,
      "days_left": 0.36,
      "num_legs": 1,
      "total_ask": 0,
      "observer_flagged": false,
      "clob_enriched": true,
      "yes_token_id": "5131435960199795569586021857615066448647736749363791491007795684022309415278",
      "no_token_id": "85612969349260851490160199327711878182585917803264673542147160816482796420402",
      "clob_yes_bid": 0.93,
      "clob_yes_ask": 0.94,
      "clob_no_bid": 0.06,
      "clob_no_ask": 0.07,
      "clob_spread": 0.01,
      "live_edge": -0.005,
      "bid_depth_5": 77099.0,
      "ask_depth_5": 444487.36,
      "enriched_at": "2026-04-04T05:22:19.073660+00:00",
      "tradeable": false
    }
  ]
}