{
  "enriched_at": "2026-04-10T23:52:25.599030+00:00",
  "elapsed_sec": 1.69,
  "count": 5,
  "tradeable_count": 1,
  "opportunities": [
    {
      "ts": "2026-04-10T23:31:25.744485+00:00",
      "strategy": "s1_negrisk_arb",
      "market_id": "0x888f5f9bae3b5dbb47ab2682fd7ad758d9ffe61c9d74c6cc064c0d9327ea6100",
      "question": "NegRisk group: Will Elon Musk post 65-89 tweets from April 9 to April 11, 2...",
      "action": "BUY_ALL_YES",
      "score": 0.9954,
      "edge": 0.1431,
      "win_probability": 1.0,
      "buy_price": 0.808,
      "ev": 0.0,
      "kelly_frac": 0.0,
      "ttl_sec": 59320,
      "executed": false,
      "reason_skipped": "daily_loss_limit",
      "trade_id": "",
      "budget_usdc": 1.0,
      "shares": 1,
      "actual_cost": 0.808,
      "unused_cash": 0.192,
      "category": "other",
      "volume_24h": 64088.25,
      "spread": 0,
      "fee": 0,
      "minutes_left": 988.7,
      "days_left": 0.69,
      "num_legs": 2,
      "total_ask": 0.808,
      "observer_flagged": false,
      "clob_enriched": false,
      "error": "gamma_fetch_failed"
    },
    {
      "ts": "2026-04-10T23:31:25.768065+00:00",
      "strategy": "s1_negrisk_arb",
      "market_id": "0xadb7e58e8bc49f689db034724fc75b1dff8ca055bba20d5a883853227974d200",
      "question": "NegRisk group: Will Roberto S\u00e1nchez Palomino win the 2026 Peruvian presiden...",
      "action": "BUY_ALL_YES",
      "score": 0.9932,
      "edge": 0.6096,
      "win_probability": 1.0,
      "buy_price": 0.362,
      "ev": 0.0,
      "kelly_frac": 0.0,
      "ttl_sec": 88118,
      "executed": false,
      "reason_skipped": "daily_loss_limit",
      "trade_id": "",
      "budget_usdc": 1.0,
      "shares": 1,
      "actual_cost": 0.362,
      "unused_cash": 0.638,
      "category": "politics",
      "volume_24h": 119294.84,
      "spread": 0,
      "fee": 0,
      "minutes_left": 1468.6,
      "days_left": 1.02,
      "num_legs": 2,
      "total_ask": 0.362,
      "observer_flagged": false,
      "clob_enriched": false,
      "error": "gamma_fetch_failed"
    },
    {
      "ts": "2026-04-10T23:31:25.792206+00:00",
      "strategy": "s1_negrisk_arb",
      "market_id": "0x038b662976e3534f906e0d7005e0f7fd282285a917eb03fd0462d14651d6e500",
      "question": "NegRisk group: Will Fulham FC win on 2026-04-11?...",
      "action": "BUY_ALL_YES",
      "score": 0.9907,
      "edge": 0.5305,
      "win_probability": 1.0,
      "buy_price": 0.44,
      "ev": 0.0,
      "kelly_frac": 0.0,
      "ttl_sec": 61116,
      "executed": false,
      "reason_skipped": "daily_loss_limit",
      "trade_id": "",
      "budget_usdc": 1.0,
      "shares": 1,
      "actual_cost": 0.44,
      "unused_cash": 0.56,
      "category": "other",
      "volume_24h": 30504.61,
      "spread": 0,
      "fee": 0,
      "minutes_left": 1018.6,
      "days_left": 0.71,
      "num_legs": 2,
      "total_ask": 0.44,
      "observer_flagged": false,
      "clob_enriched": false,
      "error": "gamma_fetch_failed"
    },
    {
      "ts": "2026-04-10T23:31:25.816139+00:00",
      "strategy": "s1_negrisk_arb",
      "market_id": "0xa0aa73aac314888dc907c8bff08f70ae71138dcd0b92ca4a3507d6a77f40fa00",
      "question": "NegRisk group: Will Sam Burns win the 2026 Masters tournament?...",
      "action": "BUY_ALL_YES",
      "score": 0.9865,
      "edge": 0.9328,
      "win_probability": 1.0,
      "buy_price": 0.067,
      "ev": 0.0,
      "kelly_frac": 0.0,
      "ttl_sec": 174518,
      "executed": false,
      "reason_skipped": "daily_loss_limit",
      "trade_id": "",
      "budget_usdc": 1.0,
      "shares": 1,
      "actual_cost": 0.067,
      "unused_cash": 0.933,
      "category": "sports",
      "volume_24h": 186362.31,
      "spread": 0,
      "fee": 0,
      "minutes_left": 2908.6,
      "days_left": 2.02,
      "num_legs": 2,
      "total_ask": 0.067,
      "observer_flagged": false,
      "clob_enriched": false,
      "error": "gamma_fetch_failed"
    },
    {
      "ts": "2026-04-10T23:31:25.720239+00:00",
      "strategy": "s10_near_resolution",
      "market_id": "1933640",
      "question": "Will Ethereum reach $2,300 on April 10?",
      "action": "BUY_NO",
      "score": 0.8053,
      "edge": 0.0282,
      "win_probability": 0.965,
      "buy_price": 0.97,
      "ev": -0.0071,
      "kelly_frac": 0.0,
      "ttl_sec": 16120,
      "executed": false,
      "reason_skipped": "daily_loss_limit",
      "trade_id": "",
      "budget_usdc": 1.0,
      "shares": 1,
      "actual_cost": 0.97,
      "unused_cash": 0.03,
      "category": "crypto",
      "volume_24h": 9065.17,
      "spread": 0.01,
      "fee": 0.001848,
      "minutes_left": 268,
      "days_left": 0.19,
      "num_legs": 1,
      "total_ask": 0,
      "observer_flagged": false,
      "clob_enriched": true,
      "yes_token_id": "23228152346534063321164728648970440853747309170820995301004665300480242908",
      "no_token_id": "17987732312244589249298562828598252523240880077624808725941746262199062815484",
      "clob_yes_bid": 0.03,
      "clob_yes_ask": 0.04,
      "clob_no_bid": 0.96,
      "clob_no_ask": 0.97,
      "clob_spread": 0.01,
      "live_edge": 0.925,
      "bid_depth_5": 3972.68,
      "ask_depth_5": 32380.62,
      "enriched_at": "2026-04-10T23:52:27.185979+00:00",
      "tradeable": true
    }
  ]
}